audio/__init__.py
audio/audio.py
audio/static/css/audio.css
audio/static/js/src/audio.js
audio/static/js/src/audio_edit.js
audio/templates/html/audio.html
audio/templates/html/audio_edit.html
audio/translations/config.yaml
audio_xblock-0.3.1.dist-info/LICENSE
audio_xblock-0.3.1.dist-info/METADATA
audio_xblock-0.3.1.dist-info/WHEEL
audio_xblock-0.3.1.dist-info/entry_points.txt
audio_xblock-0.3.1.dist-info/top_level.txt
audio_xblock-0.3.1.dist-info/RECORD
