Metadata-Version: 2.1
Name: audio-xblock
Version: 0.3.1
Summary: Audio XBlock, to play audio files in the course
License-File: LICENSE
Requires-Dist: XBlock
